luis_money_cli-0.11.2.dist-info/licenses/LICENSE
money/__init__.py
money/cli.py
money/commands/__init__.py
money/commands/accounts/__init__.py
money/commands/accounts/create.py
money/commands/accounts/list.py
money/commands/income/__init__.py
money/commands/income/create.py
money/commands/income/delete.py
money/commands/income/list.py
money/commands/savings/__init__.py
money/commands/savings/quantity.py
money/finances/__init__.py
money/finances/money.py
money/finances/month.py
money/repositories/__init__.py
money/repositories/storage.py
money/repositories/test_storage.py
luis_money_cli-0.11.2.dist-info/METADATA
luis_money_cli-0.11.2.dist-info/WHEEL
luis_money_cli-0.11.2.dist-info/entry_points.txt
luis_money_cli-0.11.2.dist-info/top_level.txt
luis_money_cli-0.11.2.dist-info/RECORD
