Metadata-Version: 2.4
Name: luis-money-cli
Version: 0.11.2
Summary: A minimal money CLI with sqlite-backed accounts
Requires-Python: >=3.13
License-File: LICENSE
Dynamic: license-file
